BERT_STEM/BertSTEM.py
BERT_STEM/Encode.py
BERT_STEM/TrainBERT4PT.py
BERT_STEM/__init__.py
bertstem-0.0.33.dist-info/LICENSE
bertstem-0.0.33.dist-info/METADATA
bertstem-0.0.33.dist-info/WHEEL
bertstem-0.0.33.dist-info/top_level.txt
bertstem-0.0.33.dist-info/RECORD
