Metadata-Version: 2.1
Name: bertstem
Version: 0.0.33
Summary: BERT model fine-tuned on chilean STEM lessons
Home-page: https://github.com/pabloveazul/BERT-STEM
Author: Pablo Uribe
Author-email: pablo.uribe@student.ecp.fr
License: UNKNOWN
Project-URL: Bug Tracker, https://github.com/pabloveazul/BERT-STEM
Platform: UNKNOWN
Classifier: Programming Language :: Python :: 3
Classifier: License :: OSI Approved :: MIT License
Classifier: Operating System :: OS Independent
Requires-Python: >=3.6
License-File: LICENSE
Requires-Dist: torch
Requires-Dist: pandas
Requires-Dist: numpy
Requires-Dist: transformers
